jsonencoder/__init__.py
jsonencoder/jsonEncoder.py
jsonencoder_gonzalo123-1.1.0.dist-info/METADATA
jsonencoder_gonzalo123-1.1.0.dist-info/WHEEL
jsonencoder_gonzalo123-1.1.0.dist-info/top_level.txt
jsonencoder_gonzalo123-1.1.0.dist-info/RECORD
