Metadata-Version: 2.1
Name: jsonencoder-gonzalo123
Version: 1.1.0
Summary: jsonencoder
Home-page: https://github.com/gonzalo123/jsonEncoder
Author: Gonzalo Ayuso
Author-email: gonzalo123@gmail.com
License: MIT
Keywords: apiclient
Platform: UNKNOWN
Classifier: Programming Language :: Python :: 3
Classifier: License :: OSI Approved :: MIT License
Classifier: Operating System :: OS Independent
Requires-Python: >=3.5
